LICENSE
README.md
bedRModv1.8.pdf
bedRMod/__init__.py
bedRMod/convert2bedRMod.py
bedRMod/helper.py
bedRMod/read.py
bedRMod/write.py
bedRMod/gui/__init__.py
bedRMod/gui/controller.py
bedRMod/gui/main.py
bedRMod/gui/view.py
bedrmod-1.8.2.dist-info/METADATA
bedrmod-1.8.2.dist-info/WHEEL
bedrmod-1.8.2.dist-info/entry_points.txt
bedrmod-1.8.2.dist-info/licenses/LICENSE
bedrmod-1.8.2.dist-info/RECORD
