Metadata-Version: 2.4
Name: bedRMod
Version: 1.8.2
Summary: Converting RNA modification data into bedRMod format.
Project-URL: Homepage, https://github.com/anmabu/bedRMod
Project-URL: Issues, https://github.com/anmabu/bedRMod/issues
Author-email: Anne Busch <anne.busch@uni-mainz.de>
License-File: LICENSE
Classifier: License :: OSI Approved :: MIT License
Classifier: Operating System :: OS Independent
Classifier: Programming Language :: Python :: 3
Requires-Python: >=3.9
Requires-Dist: numpy>=1.24.0
Requires-Dist: pandas>=2.2.2
Requires-Dist: pyside6>=6.6.1
Requires-Dist: ruamel-yaml==0.18.6
